a28/__init__.py
a28/__version__.py
a28/account.py
a28/api.py
a28/build.py
a28/cli.py
a28/config.py
a28/package.py
a28/publish.py
a28/system.py
a28/utils.py
a28-2.1.0.dist-info/entry_points.txt
a28-2.1.0.dist-info/WHEEL
a28-2.1.0.dist-info/METADATA
a28-2.1.0.dist-info/license_files/LICENSE
a28-2.1.0.dist-info/RECORD
