Metadata-Version: 2.1
Name: a28
Version: 2.1.0
Summary: A set of resources and tools to help developers create packages for the Area28 application.
License: SEE LICENSE IN LICENSE
Author-email: Area28 Technologies <dev@area28.io>
Requires-Python: >=3.7
Classifier: Environment :: Console :: Curses
Classifier: Environment :: X11 Applications :: Qt
Classifier: Intended Audience :: Developers
Classifier: License :: OSI Approved :: MIT License
Classifier: Natural Language :: English
Classifier: Operating System :: OS Independent
Classifier: Programming Language :: Python :: 3
Requires-Dist: certifi>=2022.5.18.1
Requires-Dist: coloredlogs>=15.0.1
Requires-Dist: requests>=2.27.1
Project-URL: changelog, https://github.com/area28technologies/devkit/blob/main/CHANGELOG.md
Project-URL: documentation, https://area28technologies.github.io/devkit/
Project-URL: homepage, https://github.com/area28technologies/devkit
Project-URL: repository, https://github.com/area28technologies/devkit
